mux.v
module mux (
	input switch,
	input in1,
	input in2,
	output out
	);

assign out = (switch) ? in1 : in2;

endmodule

diff_enc.v
module diff_enc(
  input clock,
  input enable,
  input reset,
  input in,
  output out);

//	Classify ports
wire clock;
wire enable;
wire reset;
wire in;
wire out;

wire xor_output;	//	Output of continuous xor
reg last_value;		//	Stores last value
reg output_selector;	// 0=xor, 1=last_value

initial begin
  output_selector = 0;
  last_value = 0;
end


//	Keep running xor
xor(xor_output, in, last_value);

//	Set up mux
mux MUX1(enable, xor_output, last_value, out);

/*
//	Set up enable wire
always @ (enable) begin
  output_selector = (enable==1) ? 1'b0 : 1'b1;
end
*/

/*
//	Use mux to switch output
always @ (enable) begin
	mux MUX1(enable, last_value, xor_output, out);
end
*/

//	If reset goes high, reset to initial conditions
always @ (posedge reset) begin
  last_value = 1'b0;
end


//	Set output from selector at each clock transition
//		and update last value
always @ (clock) begin
//	Switch output based on selector
  //out = (output_selector==1'b1) ? last_value : xor_output;
  last_value <= out;
end

endmodule

diff_enc_tb.v
module diff_enc_tb;

reg clock=0;
reg reset=0;
reg enable=0;
reg in_bs=0;
wire out_bs;


initial begin

  $dumpfile("test.vcd");
  $dumpvars(0,diff_enc_tb);
 
  //	Setup test bench inputs
  # 5 enable = 0;
      reset = 0;
	  in_bs = 0;
  
  # 5 enable = 1;
  # 5 reset = 1;
  #	2 reset = 0;

  # 5 in_bs = 0;
  # 1 in_bs = 1;
  # 1 in_bs = 0;
  # 1 in_bs = 1;
  # 1 in_bs = 0;
  # 1 in_bs = 0;
  # 1 in_bs = 1;
  # 1 in_bs = 0;
  # 1 in_bs = 0;
  # 1 in_bs = 1;
  # 1 in_bs = 1;
  # 1 in_bs = 0;
  # 1 in_bs = 1;
  # 1 in_bs = 1;
  # 1 in_bs = 0;
  # 1 in_bs = 1;
  # 1 in_bs = 0;
  # 1 in_bs = 1;
  # 1 in_bs = 0;
  # 1 in_bs = 0;
  # 1 in_bs = 1;
  reset = 1;
  # 1 in_bs = 0;
  # 1 in_bs = 0;
  # 1 in_bs = 1;
  # 1 in_bs = 1;
  # 1 in_bs = 0;
  reset = 0;
  # 1 in_bs = 1;
  # 1 in_bs = 1;
  # 1 in_bs = 0;
  # 1 in_bs = 1;
  # 1 in_bs = 0;
  # 1 in_bs = 1;
  # 1 in_bs = 0;
  # 1 in_bs = 0;
  # 1 in_bs = 1;
  # 1 in_bs = 0;
  # 1 in_bs = 0;
  # 1 in_bs = 1;
  # 1 in_bs = 1;
  # 1 in_bs = 0;
  # 1 in_bs = 1;
  # 1 in_bs = 1;
  # 1 in_bs = 0;
  # 1 in_bs = 1;
  # 1 in_bs = 0;
  # 1 in_bs = 1;
  # 1 in_bs = 0;
  # 1 in_bs = 0;
  # 1 in_bs = 1;
  # 1 in_bs = 0;
  # 1 in_bs = 0;
  enable = 0;
  # 1 in_bs = 1;
  # 1 in_bs = 1;
  # 1 in_bs = 0;
  # 1 in_bs = 1;
  # 1 in_bs = 1;
  # 1 in_bs = 0;
  # 1 in_bs = 1;
  # 1 in_bs = 0;
  # 1 in_bs = 1;
  # 1 in_bs = 0;
  # 1 in_bs = 0;
  # 1 in_bs = 1;
  enable = 1;
  # 1 in_bs = 0;
  # 1 in_bs = 0;
  # 1 in_bs = 1;
  # 1 in_bs = 1;
  # 1 in_bs = 0;
  # 1 in_bs = 1;
  # 1 in_bs = 1;
  # 1 in_bs = 0;
  # 1 in_bs = 1;
  # 1 in_bs = 0;
  # 1 in_bs = 1;
  # 1 in_bs = 0;
  # 1 in_bs = 0;
  # 1 in_bs = 1;
  # 1 in_bs = 0;
  # 1 in_bs = 0;
  # 1 in_bs = 1;
  # 1 in_bs = 1;
  # 1 in_bs = 0;
  # 1 in_bs = 1;
  # 1 in_bs = 1;
  # 1 in_bs = 0;
  # 1 in_bs = 1;
  # 1 in_bs = 0;
  # 1 in_bs = 1;
  # 1 in_bs = 0;
  # 1 in_bs = 0;
  # 1 in_bs = 1;
  # 1 in_bs = 0;
  # 1 in_bs = 0;
  # 1 in_bs = 1;
  # 1 in_bs = 1;
  # 1 in_bs = 0;
  # 1 in_bs = 1;
  # 1 in_bs = 1;
  # 1 in_bs = 0;
  # 1 in_bs = 1;
  # 1 in_bs = 0;
  # 1 in_bs = 1;
  # 1 in_bs = 0;
  # 1 in_bs = 0;
  # 1 in_bs = 1;
  # 1 in_bs = 0;
  # 1 in_bs = 0;
  # 1 in_bs = 1;
  # 1 in_bs = 1;
  # 1 in_bs = 0;
  # 1 in_bs = 1;
  # 1 in_bs = 1;
  # 1 in_bs = 0;

  # 10 $finish;
end

//	Make clock
always #1 clock = !clock;

diff_enc E1(
  .clock(clock),
  .enable(enable),
  .reset(reset),
  .in(in_bs),
  .out(out_bs)
);
  
 
 endmodule

test.vcd
$date
	Sun Apr 15 21:17:52 2018
$end
$version
	Icarus Verilog
$end
$timescale
	1s
$end
$scope module diff_enc_tb $end
$var wire 1 ! out_bs $end
$var reg 1 " clock $end
$var reg 1 # enable $end
$var reg 1 $ in_bs $end
$var reg 1 % reset $end
$scope module E1 $end
$var wire 1 " clock $end
$var wire 1 # enable $end
$var wire 1 $ in $end
$var wire 1 % reset $end
$var wire 1 & xor_output $end
$var wire 1 ! out $end
$var reg 1 ' last_value $end
$var reg 1 ( output_selector $end
$scope module MUX1 $end
$var wire 1 & in1 $end
$var wire 1 ' in2 $end
$var wire 1 # switch $end
$var wire 1 ! out $end
$upscope $end
$upscope $end
$upscope $end
$enddefinitions $end
#0
$dumpvars
0(
0'
0&
0%
0$
0#
0"
0!
$end
#1
1"
#2
0"
#3
1"
#4
0"
#5
1"
#6
0"
#7
1"
#8
0"
#9
1"
#10
0"
1#
#11
1"
#12
0"
#13
1"
#14
0"
#15
1"
1%
#16
0"
#17
1"
0%
#18
0"
#19
1"
#20
0"
#21
1"
#22
0"
#23
1!
1&
1"
1$
#24
1'
1!
1&
0"
0$
#25
0!
0&
1"
1$
#26
0'
0!
0&
0"
0$
#27
1"
#28
1!
1&
0"
1$
#29
1'
1!
1&
1"
0$
#30
0"
#31
0!
0&
1"
1$
#32
1!
1&
0'
0"
#33
1'
1!
1&
1"
0$
#34
0!
0&
0"
1$
#35
1!
1&
0'
1"
#36
1'
1!
1&
0"
0$
#37
0!
0&
1"
1$
#38
0'
0!
0&
0"
0$
#39
1!
1&
1"
1$
#40
1'
1!
1&
0"
0$
#41
1"
#42
0!
1'
0&
0"
1%
1$
#43
0'
0!
0&
1"
0$
#44
0"
#45
1!
1&
1"
1$
#46
0!
0&
1'
0"
#47
0'
0!
0&
1"
0%
0$
#48
1!
1&
0"
1$
#49
0!
0&
1'
1"
#50
0'
0!
0&
0"
0$
#51
1!
1&
1"
1$
#52
1'
1!
1&
0"
0$
#53
0!
0&
1"
1$
#54
0'
0!
0&
0"
0$
#55
1"
#56
1!
1&
0"
1$
#57
1'
1!
1&
1"
0$
#58
0"
#59
0!
0&
1"
1$
#60
1!
1&
0'
0"
#61
1'
1!
1&
1"
0$
#62
0!
0&
0"
1$
#63
1!
1&
0'
1"
#64
1'
1!
1&
0"
0$
#65
0!
0&
1"
1$
#66
0'
0!
0&
0"
0$
#67
1!
1&
1"
1$
#68
1'
1!
1&
0"
0$
#69
1"
#70
0!
0&
0"
1$
#71
0'
0!
0&
1"
0$
#72
0"
0#
#73
1&
1"
1$
#74
0"
#75
0&
1"
0$
#76
1&
0"
1$
#77
1"
#78
0&
0"
0$
#79
1&
1"
1$
#80
0&
0"
0$
#81
1&
1"
1$
#82
0&
0"
0$
#83
1"
#84
1'
0!
0&
0"
1#
1$
#85
0'
0!
0&
1"
0$
#86
0"
#87
1!
1&
1"
1$
#88
0!
0&
1'
0"
#89
0'
0!
0&
1"
0$
#90
1!
1&
0"
1$
#91
0!
0&
1'
1"
#92
0'
0!
0&
0"
0$
#93
1!
1&
1"
1$
#94
1'
1!
1&
0"
0$
#95
0!
0&
1"
1$
#96
0'
0!
0&
0"
0$
#97
1"
#98
1!
1&
0"
1$
#99
1'
1!
1&
1"
0$
#100
0"
#101
0!
0&
1"
1$
#102
1!
1&
0'
0"
#103
1'
1!
1&
1"
0$
#104
0!
0&
0"
1$
#105
1!
1&
0'
1"
#106
1'
1!
1&
0"
0$
#107
0!
0&
1"
1$
#108
0'
0!
0&
0"
0$
#109
1!
1&
1"
1$
#110
1'
1!
1&
0"
0$
#111
1"
#112
0!
0&
0"
1$
#113
0'
0!
0&
1"
0$
#114
0"
#115
1!
1&
1"
1$
#116
0!
0&
1'
0"
#117
0'
0!
0&
1"
0$
#118
1!
1&
0"
1$
#119
0!
0&
1'
1"
#120
0'
0!
0&
0"
0$
#121
1!
1&
1"
1$
#122
1'
1!
1&
0"
0$
#123
0!
0&
1"
1$
#124
0'
0!
0&
0"
0$
#125
1"
#126
1!
1&
0"
1$
#127
1'
1!
1&
1"
0$
#128
0"
#129
0!
0&
1"
1$
#130
1!
1&
0'
0"
#131
1'
1!
1&
1"
0$
#132
0!
0&
0"
1$
#133
1!
1&
0'
1"
#134
1'
1!
1&
0"
0$
